llm_werewolf/__init__.py
llm_werewolf/cli.py
llm_werewolf/ai/__init__.py
llm_werewolf/ai/agents.py
llm_werewolf/ai/message.py
llm_werewolf/config/__init__.py
llm_werewolf/config/game_config.py
llm_werewolf/config/role_presets.py
llm_werewolf/core/__init__.py
llm_werewolf/core/actions.py
llm_werewolf/core/events.py
llm_werewolf/core/game_engine.py
llm_werewolf/core/game_state.py
llm_werewolf/core/player.py
llm_werewolf/core/victory.py
llm_werewolf/core/roles/__init__.py
llm_werewolf/core/roles/base.py
llm_werewolf/core/roles/neutral.py
llm_werewolf/core/roles/villager.py
llm_werewolf/core/roles/werewolf.py
llm_werewolf/ui/__init__.py
llm_werewolf/ui/styles.py
llm_werewolf/ui/tui_app.py
llm_werewolf/ui/components/__init__.py
llm_werewolf/ui/components/chat_panel.py
llm_werewolf/ui/components/debug_panel.py
llm_werewolf/ui/components/game_panel.py
llm_werewolf/ui/components/player_panel.py
llm_werewolf/utils/__init__.py
llm_werewolf/utils/logger.py
llm_werewolf/utils/validator.py
llm_werewolf-0.1.0.dist-info/METADATA
llm_werewolf-0.1.0.dist-info/WHEEL
llm_werewolf-0.1.0.dist-info/entry_points.txt
llm_werewolf-0.1.0.dist-info/licenses/LICENSE
llm_werewolf-0.1.0.dist-info/RECORD
