Metadata-Version: 2.4
Name: llm_werewolf
Version: 0.1.0
Summary: AI-powered Werewolf game with LLM integration and TUI interface
Project-URL: Homepage, https://mai0313.github.io/llm_werewolf
Project-URL: Repository, https://github.com/Mai0313/llm_werewolf
Author-email: Wei <mai@mai0313.com>
License: MIT
License-File: LICENSE
Requires-Python: >=3.10
Requires-Dist: openai>=2.5.0
Requires-Dist: pydantic-settings>=2.0.0
Requires-Dist: pydantic>=2.0.0
Requires-Dist: python-dotenv>=1.0.0
Requires-Dist: pyyaml>=6.0.0
Requires-Dist: rich>=13.0.0
Requires-Dist: textual>=0.40.0
